defn_cdktf_provider_cloudflare/__init__.py
defn_cdktf_provider_cloudflare/main.py
defn_cdktf_provider_cloudflare/_jsii/__init__.py
defn_cdktf_provider_cloudflare/_jsii/cloudflare_cloudflare@0.0.0.jsii.tgz
defn_cdktf_provider_cloudflare/_jsii/main.py
defn_cdktf_provider_cloudflare-0.4.1.dist-info/METADATA
defn_cdktf_provider_cloudflare-0.4.1.dist-info/WHEEL
defn_cdktf_provider_cloudflare-0.4.1.dist-info/namespace_packages.txt
defn_cdktf_provider_cloudflare-0.4.1.dist-info/top_level.txt
defn_cdktf_provider_cloudflare-0.4.1.dist-info/RECORD
