Metadata-Version: 2.1
Name: defn-cdktf-provider-cloudflare
Version: 0.4.1
Summary: UNKNOWN
Home-page: UNKNOWN
License: UNKNOWN
Platform: UNKNOWN
Requires-Python: <4,>=3.8
Requires-Dist: cdktf (==0.11.1)
Requires-Dist: constructs (==10.1.25)
Requires-Dist: jsii (==1.59.0)
Requires-Dist: publication (==0.0.3)
Requires-Dist: typing-extensions (==4.2.0)
